{
    "mmoe_models": [{"model_type": "mmoe_CNN1d", "params": {"n1": 64, "n2": 128, "n3": 256,"dropout_rate": 0.2,"num_experts": 3}},
                {"model_type": "mmoe_CNN1d", "params": {"n1": 64, "n2": 128, "n3": 256,"dropout_rate": 0.2,"num_experts": 3}},
                {"model_type": "mmoe_CNN1d", "params": {"n1": 64, "n2": 128, "n3": 256, "dropout_rate": 0.2,"num_experts": 3}},
                {"model_type": "mmoe_CNN1d", "params": {"n1": 64, "n2": 128, "n3": 256,"dropout_rate": 0.2, "num_experts": 3}},
                {"model_type": "mmoe_CNN1d", "params": {"n1": 64, "n2": 128, "n3": 256,"dropout_rate": 0.2, "num_experts": 3}},
                {"model_type": "mmoe_CNN1d", "params": {"n1": 64, "n2": 128, "n3": 256,"dropout_rate": 0.2, "num_experts": 3}},
                {"model_type": "mmoe_CNN1d", "params": {"n1": 64, "n2": 128, "n3": 256, "dropout_rate": 0.2,"num_experts": 3}},
                {"model_type": "mmoe_CNN1d", "params": {"n1": 64, "n2": 128, "n3": 256,"dropout_rate": 0.2,"num_experts": 3}},
                {"model_type": "mmoe_CNN1d", "params": {"n1": 64, "n2": 128, "n3": 256, "dropout_rate": 0.2,"num_experts": 3}},
                {"model_type": "mmoe_CNN1d", "params": {"n1": 64, "n2": 128, "n3": 256, "dropout_rate": 0.2, "num_experts": 3}}
              ],
    "models": [{"model_type": "CNN1d", "params": {"n1": 64, "n2": 128, "n3": 256,"dropout_rate": 0.2,"num_experts": 3}},
                {"model_type": "CNN1d", "params": {"n1": 64, "n2": 128, "n3": 256,"dropout_rate": 0.2,"num_experts": 3}},
                {"model_type": "CNN1d", "params": {"n1": 64, "n2": 128, "n3": 256, "dropout_rate": 0.2,"num_experts": 3}},
                {"model_type": "CNN1d", "params": {"n1": 64, "n2": 128, "n3": 256,"dropout_rate": 0.2, "num_experts": 3}},
                {"model_type": "CNN1d", "params": {"n1": 64, "n2": 128, "n3": 256,"dropout_rate": 0.2, "num_experts": 3}},
                {"model_type": "CNN1d", "params": {"n1": 64, "n2": 128, "n3": 256,"dropout_rate": 0.2, "num_experts": 3}},
                {"model_type": "CNN1d", "params": {"n1": 64, "n2": 128, "n3": 256, "dropout_rate": 0.2,"num_experts": 3}},
                {"model_type": "CNN1d", "params": {"n1": 64, "n2": 128, "n3": 256,"dropout_rate": 0.2,"num_experts": 3}},
                {"model_type": "CNN1d", "params": {"n1": 64, "n2": 128, "n3": 256, "dropout_rate": 0.2,"num_experts": 3}},
                {"model_type": "CNN1d", "params": {"n1": 64, "n2": 128, "n3": 256, "dropout_rate": 0.2, "num_experts": 3}}
              ],

    "pre_train_params": {"min_delta": 0.005, "patience": 3,
                     "batch_size": 500, "epochs": 4, "is_shuffle": True,
                     "verbose": 1},
    "model_saved_dir": None,
    "model_saved_names" : ["model0","model1","model2","model3","model4","model5","model6","model7","model8","model9"],
    "early_stopping" : True,
    "N_parties": 10,
    "N_experts": 3,
    "N_samples_per_class": 100,
    "N_alignment": 5000,
    "private_classes": [0,1],
    "public_classes": [0,1],
    "is_show": False,
    "N_rounds": 20,
    "N_logits_matching_round": 6,
    "N_private_training_round": 20,
    "private_training_batchsize" : 32,
    "logits_matching_batchsize": 200,
    "EMNIST_dir": None,
    "result_save_dir": "./result_YELP_balanced/",
    "public_dataset": "dataset/yelp/review_Automotive_star_15_sub8000.json",
    "private_dataset_train": "dataset/yelp/iid/review_Restaurants_star_15_sub1000000.json",
    "private_dataset_test": "dataset/yelp/iid/review_Restaurants_star_15_sub10000.json",
    "word_vector_file": "glove.6B.50d.txt",
    "max_sequence_length": 80,
    "max_words_num": 200000,
    "embedding_dim": 50
}
